{
  "17": {
    "translation": "Manx Gaelic (Esther Jonah 4 Gospels)",
    "abbreviation": "manxgaelic",
    "lang": "gv",
    "language": "Manx Gaelic",
    "direction": "LTR",
    "encoding": "",
    "nr": 17,
    "name": "Esther",
    "url": "https://getbible.net/v2/manxgaelic/17.json",
    "sha": "c13dc0edbfa2258486307304db6ec64fa4d232c8"
  },
  "32": {
    "translation": "Manx Gaelic (Esther Jonah 4 Gospels)",
    "abbreviation": "manxgaelic",
    "lang": "gv",
    "language": "Manx Gaelic",
    "direction": "LTR",
    "encoding": "",
    "nr": 32,
    "name": "Jonah",
    "url": "https://getbible.net/v2/manxgaelic/32.json",
    "sha": "e687eeceeacaa1c91383e9297dc16ccd18bbc97b"
  },
  "40": {
    "translation": "Manx Gaelic (Esther Jonah 4 Gospels)",
    "abbreviation": "manxgaelic",
    "lang": "gv",
    "language": "Manx Gaelic",
    "direction": "LTR",
    "encoding": "",
    "nr": 40,
    "name": "Matthew",
    "url": "https://getbible.net/v2/manxgaelic/40.json",
    "sha": "50ccca5a0bac03443a2acd86c833d4821885e6c8"
  },
  "42": {
    "translation": "Manx Gaelic (Esther Jonah 4 Gospels)",
    "abbreviation": "manxgaelic",
    "lang": "gv",
    "language": "Manx Gaelic",
    "direction": "LTR",
    "encoding": "",
    "nr": 42,
    "name": "Luke",
    "url": "https://getbible.net/v2/manxgaelic/42.json",
    "sha": "cee10d0b30c117c46aa107eb3cf19a4d0eb64b82"
  },
  "43": {
    "translation": "Manx Gaelic (Esther Jonah 4 Gospels)",
    "abbreviation": "manxgaelic",
    "lang": "gv",
    "language": "Manx Gaelic",
    "direction": "LTR",
    "encoding": "",
    "nr": 43,
    "name": "John",
    "url": "https://getbible.net/v2/manxgaelic/43.json",
    "sha": "79cc3775c19df0abf88643e2c5f2e616a9d8f412"
  }
}
