{
  "1": {
    "translation": "Albanian Bible",
    "abbreviation": "alb",
    "lang": "sq",
    "language": "Albanian",
    "direction": "LTR",
    "encoding": "UTF-8",
    "nr": 1,
    "name": "Genesis",
    "url": "https://api.getbible.net/v2/alb/1.json",
    "sha": "40f777e1aced5d0b72ae455603e0fae0a715e2cf"
  },
  "2": {
    "translation": "Albanian Bible",
    "abbreviation": "alb",
    "lang": "sq",
    "language": "Albanian",
    "direction": "LTR",
    "encoding": "UTF-8",
    "nr": 2,
    "name": "Exodus",
    "url": "https://api.getbible.net/v2/alb/2.json",
    "sha": "9634c576c830bd66a530621ab145559c31fe8268"
  },
  "3": {
    "translation": "Albanian Bible",
    "abbreviation": "alb",
    "lang": "sq",
    "language": "Albanian",
    "direction": "LTR",
    "encoding": "UTF-8",
    "nr": 3,
    "name": "Leviticus",
    "url": "https://api.getbible.net/v2/alb/3.json",
    "sha": "7695de7835c2acefff29a040b302e6d929e6e7c3"
  },
  "4": {
    "translation": "Albanian Bible",
    "abbreviation": "alb",
    "lang": "sq",
    "language": "Albanian",
    "direction": "LTR",
    "encoding": "UTF-8",
    "nr": 4,
    "name": "Numbers",
    "url": "https://api.getbible.net/v2/alb/4.json",
    "sha": "fa065babb0de55c19556bf48233bbb1176bedae2"
  },
  "5": {
    "translation": "Albanian Bible",
    "abbreviation": "alb",
    "lang": "sq",
    "language": "Albanian",
    "direction": "LTR",
    "encoding": "UTF-8",
    "nr": 5,
    "name": "Deuteronomy",
    "url": "https://api.getbible.net/v2/alb/5.json",
    "sha": "7a727b94ab8202e56b8d6fad09952e55b4883bae"
  },
  "6": {
    "translation": "Albanian Bible",
    "abbreviation": "alb",
    "lang": "sq",
    "language": "Albanian",
    "direction": "LTR",
    "encoding": "UTF-8",
    "nr": 6,
    "name": "Joshua",
    "url": "https://api.getbible.net/v2/alb/6.json",
    "sha": "3208decd20cd88bbb357336a7fd28380219ac27c"
  },
  "7": {
    "translation": "Albanian Bible",
    "abbreviation": "alb",
    "lang": "sq",
    "language": "Albanian",
    "direction": "LTR",
    "encoding": "UTF-8",
    "nr": 7,
    "name": "Judges",
    "url": "https://api.getbible.net/v2/alb/7.json",
    "sha": "48bc1f0b330b6ee9797949e5993e9c8062814756"
  },
  "8": {
    "translation": "Albanian Bible",
    "abbreviation": "alb",
    "lang": "sq",
    "language": "Albanian",
    "direction": "LTR",
    "encoding": "UTF-8",
    "nr": 8,
    "name": "Ruth",
    "url": "https://api.getbible.net/v2/alb/8.json",
    "sha": "e173de4f2c45e758029a2430432a130f36a904f7"
  },
  "9": {
    "translation": "Albanian Bible",
    "abbreviation": "alb",
    "lang": "sq",
    "language": "Albanian",
    "direction": "LTR",
    "encoding": "UTF-8",
    "nr": 9,
    "name": "1 Samuel",
    "url": "https://api.getbible.net/v2/alb/9.json",
    "sha": "1fd788a9170d0aaeed21a1bf2172f4f6fb5b1faf"
  },
  "10": {
    "translation": "Albanian Bible",
    "abbreviation": "alb",
    "lang": "sq",
    "language": "Albanian",
    "direction": "LTR",
    "encoding": "UTF-8",
    "nr": 10,
    "name": "2 Samuel",
    "url": "https://api.getbible.net/v2/alb/10.json",
    "sha": "a24b6e4e71f9949047bb372174fe45ea24e56c2d"
  },
  "11": {
    "translation": "Albanian Bible",
    "abbreviation": "alb",
    "lang": "sq",
    "language": "Albanian",
    "direction": "LTR",
    "encoding": "UTF-8",
    "nr": 11,
    "name": "1 Kings",
    "url": "https://api.getbible.net/v2/alb/11.json",
    "sha": "5e60cb0d7cf87173f5d2bf4b666902403ff155f5"
  },
  "12": {
    "translation": "Albanian Bible",
    "abbreviation": "alb",
    "lang": "sq",
    "language": "Albanian",
    "direction": "LTR",
    "encoding": "UTF-8",
    "nr": 12,
    "name": "2 Kings",
    "url": "https://api.getbible.net/v2/alb/12.json",
    "sha": "39483d723887cd6496db3eda893102912d988f32"
  },
  "13": {
    "translation": "Albanian Bible",
    "abbreviation": "alb",
    "lang": "sq",
    "language": "Albanian",
    "direction": "LTR",
    "encoding": "UTF-8",
    "nr": 13,
    "name": "1 Chronicles",
    "url": "https://api.getbible.net/v2/alb/13.json",
    "sha": "eaa16eac66c39d91843cb44babb9c120221d1d3a"
  },
  "14": {
    "translation": "Albanian Bible",
    "abbreviation": "alb",
    "lang": "sq",
    "language": "Albanian",
    "direction": "LTR",
    "encoding": "UTF-8",
    "nr": 14,
    "name": "2 Chronicles",
    "url": "https://api.getbible.net/v2/alb/14.json",
    "sha": "53c92a41a8e56f140f9d8a5b517ec2cfb85ed70e"
  },
  "15": {
    "translation": "Albanian Bible",
    "abbreviation": "alb",
    "lang": "sq",
    "language": "Albanian",
    "direction": "LTR",
    "encoding": "UTF-8",
    "nr": 15,
    "name": "Ezra",
    "url": "https://api.getbible.net/v2/alb/15.json",
    "sha": "24c4e7e8187727a0e8d30ad283923f854c1a9bd4"
  },
  "16": {
    "translation": "Albanian Bible",
    "abbreviation": "alb",
    "lang": "sq",
    "language": "Albanian",
    "direction": "LTR",
    "encoding": "UTF-8",
    "nr": 16,
    "name": "Nehemiah",
    "url": "https://api.getbible.net/v2/alb/16.json",
    "sha": "d6c99c3f01d82192ce8898cadbdf98072bcf759e"
  },
  "17": {
    "translation": "Albanian Bible",
    "abbreviation": "alb",
    "lang": "sq",
    "language": "Albanian",
    "direction": "LTR",
    "encoding": "UTF-8",
    "nr": 17,
    "name": "Esther",
    "url": "https://api.getbible.net/v2/alb/17.json",
    "sha": "82050a7f9c5dd5e8609c341f84befff7dc4d36ff"
  },
  "18": {
    "translation": "Albanian Bible",
    "abbreviation": "alb",
    "lang": "sq",
    "language": "Albanian",
    "direction": "LTR",
    "encoding": "UTF-8",
    "nr": 18,
    "name": "Job",
    "url": "https://api.getbible.net/v2/alb/18.json",
    "sha": "43715ceedc13adeb7302f1a4ab0232049cc4f79a"
  },
  "19": {
    "translation": "Albanian Bible",
    "abbreviation": "alb",
    "lang": "sq",
    "language": "Albanian",
    "direction": "LTR",
    "encoding": "UTF-8",
    "nr": 19,
    "name": "Psalms",
    "url": "https://api.getbible.net/v2/alb/19.json",
    "sha": "dbc36a440914a971e6b073e59f2d9828b71a8e32"
  },
  "20": {
    "translation": "Albanian Bible",
    "abbreviation": "alb",
    "lang": "sq",
    "language": "Albanian",
    "direction": "LTR",
    "encoding": "UTF-8",
    "nr": 20,
    "name": "Proverbs",
    "url": "https://api.getbible.net/v2/alb/20.json",
    "sha": "736a652a03450dd1381e62de4f704d55839ec3ae"
  },
  "21": {
    "translation": "Albanian Bible",
    "abbreviation": "alb",
    "lang": "sq",
    "language": "Albanian",
    "direction": "LTR",
    "encoding": "UTF-8",
    "nr": 21,
    "name": "Ecclesiastes",
    "url": "https://api.getbible.net/v2/alb/21.json",
    "sha": "d36ce6c4589a341125b647233bf4b01493503a13"
  },
  "22": {
    "translation": "Albanian Bible",
    "abbreviation": "alb",
    "lang": "sq",
    "language": "Albanian",
    "direction": "LTR",
    "encoding": "UTF-8",
    "nr": 22,
    "name": "Song of Solomon",
    "url": "https://api.getbible.net/v2/alb/22.json",
    "sha": "eb846dea69e3ffa449a6d9efd6048bd1b7b75020"
  },
  "23": {
    "translation": "Albanian Bible",
    "abbreviation": "alb",
    "lang": "sq",
    "language": "Albanian",
    "direction": "LTR",
    "encoding": "UTF-8",
    "nr": 23,
    "name": "Isaiah",
    "url": "https://api.getbible.net/v2/alb/23.json",
    "sha": "635b2d5dc5d2c9094fce827a11011dfa3d315db7"
  },
  "24": {
    "translation": "Albanian Bible",
    "abbreviation": "alb",
    "lang": "sq",
    "language": "Albanian",
    "direction": "LTR",
    "encoding": "UTF-8",
    "nr": 24,
    "name": "Jeremiah",
    "url": "https://api.getbible.net/v2/alb/24.json",
    "sha": "1821b2ff17546b08dac1f22d60e0631938bb20ef"
  },
  "25": {
    "translation": "Albanian Bible",
    "abbreviation": "alb",
    "lang": "sq",
    "language": "Albanian",
    "direction": "LTR",
    "encoding": "UTF-8",
    "nr": 25,
    "name": "Lamentations",
    "url": "https://api.getbible.net/v2/alb/25.json",
    "sha": "bcda0535edd6395040ca6ed4a478521fe1b177d0"
  },
  "26": {
    "translation": "Albanian Bible",
    "abbreviation": "alb",
    "lang": "sq",
    "language": "Albanian",
    "direction": "LTR",
    "encoding": "UTF-8",
    "nr": 26,
    "name": "Ezekiel",
    "url": "https://api.getbible.net/v2/alb/26.json",
    "sha": "753cd877cd8217d6670f7e62b243800d1ed48bcd"
  },
  "27": {
    "translation": "Albanian Bible",
    "abbreviation": "alb",
    "lang": "sq",
    "language": "Albanian",
    "direction": "LTR",
    "encoding": "UTF-8",
    "nr": 27,
    "name": "Daniel",
    "url": "https://api.getbible.net/v2/alb/27.json",
    "sha": "723615eef2ca15b941bc24354a5b6cf057fea9b9"
  },
  "28": {
    "translation": "Albanian Bible",
    "abbreviation": "alb",
    "lang": "sq",
    "language": "Albanian",
    "direction": "LTR",
    "encoding": "UTF-8",
    "nr": 28,
    "name": "Hosea",
    "url": "https://api.getbible.net/v2/alb/28.json",
    "sha": "3e59c75eb964ac8f5aba9dc607e9ab7fb7e3836d"
  },
  "29": {
    "translation": "Albanian Bible",
    "abbreviation": "alb",
    "lang": "sq",
    "language": "Albanian",
    "direction": "LTR",
    "encoding": "UTF-8",
    "nr": 29,
    "name": "Joel",
    "url": "https://api.getbible.net/v2/alb/29.json",
    "sha": "a00ae5f414fc02157f91aaecab9a0e6eb895f7ff"
  },
  "30": {
    "translation": "Albanian Bible",
    "abbreviation": "alb",
    "lang": "sq",
    "language": "Albanian",
    "direction": "LTR",
    "encoding": "UTF-8",
    "nr": 30,
    "name": "Amos",
    "url": "https://api.getbible.net/v2/alb/30.json",
    "sha": "afdc9c5c383bee9de5f9090c9acdf135bec60c72"
  },
  "31": {
    "translation": "Albanian Bible",
    "abbreviation": "alb",
    "lang": "sq",
    "language": "Albanian",
    "direction": "LTR",
    "encoding": "UTF-8",
    "nr": 31,
    "name": "Obadiah",
    "url": "https://api.getbible.net/v2/alb/31.json",
    "sha": "2ff05d580d5a0ed508dc7ee94fb63c4d0978e2a1"
  },
  "32": {
    "translation": "Albanian Bible",
    "abbreviation": "alb",
    "lang": "sq",
    "language": "Albanian",
    "direction": "LTR",
    "encoding": "UTF-8",
    "nr": 32,
    "name": "Jonah",
    "url": "https://api.getbible.net/v2/alb/32.json",
    "sha": "d111c33846e23c94db776662b3ab3e9ba12c525e"
  },
  "33": {
    "translation": "Albanian Bible",
    "abbreviation": "alb",
    "lang": "sq",
    "language": "Albanian",
    "direction": "LTR",
    "encoding": "UTF-8",
    "nr": 33,
    "name": "Micah",
    "url": "https://api.getbible.net/v2/alb/33.json",
    "sha": "744675a3870a6fe4f41b7252eb9d6a8a8c4cf68d"
  },
  "34": {
    "translation": "Albanian Bible",
    "abbreviation": "alb",
    "lang": "sq",
    "language": "Albanian",
    "direction": "LTR",
    "encoding": "UTF-8",
    "nr": 34,
    "name": "Nahum",
    "url": "https://api.getbible.net/v2/alb/34.json",
    "sha": "faab9e65bfd816bea8a0109e2a2b93bb75b32985"
  },
  "35": {
    "translation": "Albanian Bible",
    "abbreviation": "alb",
    "lang": "sq",
    "language": "Albanian",
    "direction": "LTR",
    "encoding": "UTF-8",
    "nr": 35,
    "name": "Habakkuk",
    "url": "https://api.getbible.net/v2/alb/35.json",
    "sha": "13130471ff7d304072b5e507906b9c076d57830e"
  },
  "36": {
    "translation": "Albanian Bible",
    "abbreviation": "alb",
    "lang": "sq",
    "language": "Albanian",
    "direction": "LTR",
    "encoding": "UTF-8",
    "nr": 36,
    "name": "Zephaniah",
    "url": "https://api.getbible.net/v2/alb/36.json",
    "sha": "90e5d280ba56d453de88cca3c93c02c0ea642547"
  },
  "37": {
    "translation": "Albanian Bible",
    "abbreviation": "alb",
    "lang": "sq",
    "language": "Albanian",
    "direction": "LTR",
    "encoding": "UTF-8",
    "nr": 37,
    "name": "Haggai",
    "url": "https://api.getbible.net/v2/alb/37.json",
    "sha": "b8140bf3da1349e745c30931af35829da3f93db6"
  },
  "38": {
    "translation": "Albanian Bible",
    "abbreviation": "alb",
    "lang": "sq",
    "language": "Albanian",
    "direction": "LTR",
    "encoding": "UTF-8",
    "nr": 38,
    "name": "Zechariah",
    "url": "https://api.getbible.net/v2/alb/38.json",
    "sha": "b86cf99812fc9a1d92723154bb2926f8e6a31dc0"
  },
  "39": {
    "translation": "Albanian Bible",
    "abbreviation": "alb",
    "lang": "sq",
    "language": "Albanian",
    "direction": "LTR",
    "encoding": "UTF-8",
    "nr": 39,
    "name": "Malachi",
    "url": "https://api.getbible.net/v2/alb/39.json",
    "sha": "76f38d3c059b566b3e7f8e76d80f1fa4065ba056"
  },
  "40": {
    "translation": "Albanian Bible",
    "abbreviation": "alb",
    "lang": "sq",
    "language": "Albanian",
    "direction": "LTR",
    "encoding": "UTF-8",
    "nr": 40,
    "name": "Matthew",
    "url": "https://api.getbible.net/v2/alb/40.json",
    "sha": "191f94c38137f3490dd42bdbdd78068371d2184a"
  },
  "41": {
    "translation": "Albanian Bible",
    "abbreviation": "alb",
    "lang": "sq",
    "language": "Albanian",
    "direction": "LTR",
    "encoding": "UTF-8",
    "nr": 41,
    "name": "Mark",
    "url": "https://api.getbible.net/v2/alb/41.json",
    "sha": "866e784a8c80dc50b5b4b845be6342e5a5c20598"
  },
  "42": {
    "translation": "Albanian Bible",
    "abbreviation": "alb",
    "lang": "sq",
    "language": "Albanian",
    "direction": "LTR",
    "encoding": "UTF-8",
    "nr": 42,
    "name": "Luke",
    "url": "https://api.getbible.net/v2/alb/42.json",
    "sha": "de5d8b1f9f28dd6f4eb097d414449b649861f7ff"
  },
  "43": {
    "translation": "Albanian Bible",
    "abbreviation": "alb",
    "lang": "sq",
    "language": "Albanian",
    "direction": "LTR",
    "encoding": "UTF-8",
    "nr": 43,
    "name": "John",
    "url": "https://api.getbible.net/v2/alb/43.json",
    "sha": "4b7692e9144281b8d2891a2b8982cc6657827130"
  },
  "44": {
    "translation": "Albanian Bible",
    "abbreviation": "alb",
    "lang": "sq",
    "language": "Albanian",
    "direction": "LTR",
    "encoding": "UTF-8",
    "nr": 44,
    "name": "Acts",
    "url": "https://api.getbible.net/v2/alb/44.json",
    "sha": "3d7880614f5d30a09261e566a5b2e5ae48054fa0"
  },
  "45": {
    "translation": "Albanian Bible",
    "abbreviation": "alb",
    "lang": "sq",
    "language": "Albanian",
    "direction": "LTR",
    "encoding": "UTF-8",
    "nr": 45,
    "name": "Romans",
    "url": "https://api.getbible.net/v2/alb/45.json",
    "sha": "2632fba0b8bfc5c41e374a6745c56972551bf620"
  },
  "46": {
    "translation": "Albanian Bible",
    "abbreviation": "alb",
    "lang": "sq",
    "language": "Albanian",
    "direction": "LTR",
    "encoding": "UTF-8",
    "nr": 46,
    "name": "1 Corinthians",
    "url": "https://api.getbible.net/v2/alb/46.json",
    "sha": "e8672a96aba681967f90015185b055cbba9f38ce"
  },
  "47": {
    "translation": "Albanian Bible",
    "abbreviation": "alb",
    "lang": "sq",
    "language": "Albanian",
    "direction": "LTR",
    "encoding": "UTF-8",
    "nr": 47,
    "name": "2 Corinthians",
    "url": "https://api.getbible.net/v2/alb/47.json",
    "sha": "ff7712721a66286de97ea09d7f85c2987c7c59ec"
  },
  "48": {
    "translation": "Albanian Bible",
    "abbreviation": "alb",
    "lang": "sq",
    "language": "Albanian",
    "direction": "LTR",
    "encoding": "UTF-8",
    "nr": 48,
    "name": "Galatians",
    "url": "https://api.getbible.net/v2/alb/48.json",
    "sha": "6e9de29ab4d671cecc1dbbdad0c8f691f45e7a30"
  },
  "49": {
    "translation": "Albanian Bible",
    "abbreviation": "alb",
    "lang": "sq",
    "language": "Albanian",
    "direction": "LTR",
    "encoding": "UTF-8",
    "nr": 49,
    "name": "Ephesians",
    "url": "https://api.getbible.net/v2/alb/49.json",
    "sha": "d375627eb15ed28912ccda1f3ca69832df31ad8f"
  },
  "50": {
    "translation": "Albanian Bible",
    "abbreviation": "alb",
    "lang": "sq",
    "language": "Albanian",
    "direction": "LTR",
    "encoding": "UTF-8",
    "nr": 50,
    "name": "Philippians",
    "url": "https://api.getbible.net/v2/alb/50.json",
    "sha": "7bf5016c21e685100d320af059fcb5f2473169e2"
  },
  "51": {
    "translation": "Albanian Bible",
    "abbreviation": "alb",
    "lang": "sq",
    "language": "Albanian",
    "direction": "LTR",
    "encoding": "UTF-8",
    "nr": 51,
    "name": "Colossians",
    "url": "https://api.getbible.net/v2/alb/51.json",
    "sha": "28cac9b550b979d328ad73de9646c23b0523a5fe"
  },
  "52": {
    "translation": "Albanian Bible",
    "abbreviation": "alb",
    "lang": "sq",
    "language": "Albanian",
    "direction": "LTR",
    "encoding": "UTF-8",
    "nr": 52,
    "name": "1 Thessalonians",
    "url": "https://api.getbible.net/v2/alb/52.json",
    "sha": "a8f68c179f2f4df717908abf730668fb82bb935e"
  },
  "53": {
    "translation": "Albanian Bible",
    "abbreviation": "alb",
    "lang": "sq",
    "language": "Albanian",
    "direction": "LTR",
    "encoding": "UTF-8",
    "nr": 53,
    "name": "2 Thessalonians",
    "url": "https://api.getbible.net/v2/alb/53.json",
    "sha": "279acbf2ab56cd099eb1527c2cbd4b2b18fb8e2a"
  },
  "54": {
    "translation": "Albanian Bible",
    "abbreviation": "alb",
    "lang": "sq",
    "language": "Albanian",
    "direction": "LTR",
    "encoding": "UTF-8",
    "nr": 54,
    "name": "1 Timothy",
    "url": "https://api.getbible.net/v2/alb/54.json",
    "sha": "8507090fe1f6e1bc4a1c42a31d2dad03a11ff38c"
  },
  "55": {
    "translation": "Albanian Bible",
    "abbreviation": "alb",
    "lang": "sq",
    "language": "Albanian",
    "direction": "LTR",
    "encoding": "UTF-8",
    "nr": 55,
    "name": "2 Timothy",
    "url": "https://api.getbible.net/v2/alb/55.json",
    "sha": "240747df450dc844137de1eb3493502ef692283d"
  },
  "56": {
    "translation": "Albanian Bible",
    "abbreviation": "alb",
    "lang": "sq",
    "language": "Albanian",
    "direction": "LTR",
    "encoding": "UTF-8",
    "nr": 56,
    "name": "Titus",
    "url": "https://api.getbible.net/v2/alb/56.json",
    "sha": "7bb3dd8e7994caa3f9f3d3b36504b5020b54da52"
  },
  "57": {
    "translation": "Albanian Bible",
    "abbreviation": "alb",
    "lang": "sq",
    "language": "Albanian",
    "direction": "LTR",
    "encoding": "UTF-8",
    "nr": 57,
    "name": "Philemon",
    "url": "https://api.getbible.net/v2/alb/57.json",
    "sha": "8586666d2f7811e34b60004f2f5c2d5ab47bafb0"
  },
  "58": {
    "translation": "Albanian Bible",
    "abbreviation": "alb",
    "lang": "sq",
    "language": "Albanian",
    "direction": "LTR",
    "encoding": "UTF-8",
    "nr": 58,
    "name": "Hebrews",
    "url": "https://api.getbible.net/v2/alb/58.json",
    "sha": "7ba3c535d3fb87dcf81a06185ef061c0153f454c"
  },
  "59": {
    "translation": "Albanian Bible",
    "abbreviation": "alb",
    "lang": "sq",
    "language": "Albanian",
    "direction": "LTR",
    "encoding": "UTF-8",
    "nr": 59,
    "name": "James",
    "url": "https://api.getbible.net/v2/alb/59.json",
    "sha": "01fd04da9559ba987c7459510bcc49d6ffac2696"
  },
  "60": {
    "translation": "Albanian Bible",
    "abbreviation": "alb",
    "lang": "sq",
    "language": "Albanian",
    "direction": "LTR",
    "encoding": "UTF-8",
    "nr": 60,
    "name": "1 Peter",
    "url": "https://api.getbible.net/v2/alb/60.json",
    "sha": "17b1abb14de757c169cd669a4075f1e4b3cf5dbd"
  },
  "61": {
    "translation": "Albanian Bible",
    "abbreviation": "alb",
    "lang": "sq",
    "language": "Albanian",
    "direction": "LTR",
    "encoding": "UTF-8",
    "nr": 61,
    "name": "2 Peter",
    "url": "https://api.getbible.net/v2/alb/61.json",
    "sha": "9710d12915e8f7104a407bc26e6a04319a806834"
  },
  "62": {
    "translation": "Albanian Bible",
    "abbreviation": "alb",
    "lang": "sq",
    "language": "Albanian",
    "direction": "LTR",
    "encoding": "UTF-8",
    "nr": 62,
    "name": "1 John",
    "url": "https://api.getbible.net/v2/alb/62.json",
    "sha": "57bddaafe7f080b9e7246a8cf85bedb06a529761"
  },
  "63": {
    "translation": "Albanian Bible",
    "abbreviation": "alb",
    "lang": "sq",
    "language": "Albanian",
    "direction": "LTR",
    "encoding": "UTF-8",
    "nr": 63,
    "name": "2 John",
    "url": "https://api.getbible.net/v2/alb/63.json",
    "sha": "8e800dfbc1f2e27525a6cd55d03aa9a129e6249e"
  },
  "64": {
    "translation": "Albanian Bible",
    "abbreviation": "alb",
    "lang": "sq",
    "language": "Albanian",
    "direction": "LTR",
    "encoding": "UTF-8",
    "nr": 64,
    "name": "3 John",
    "url": "https://api.getbible.net/v2/alb/64.json",
    "sha": "b6e5b699b1889bd5af01d539b39773c70f82785a"
  },
  "65": {
    "translation": "Albanian Bible",
    "abbreviation": "alb",
    "lang": "sq",
    "language": "Albanian",
    "direction": "LTR",
    "encoding": "UTF-8",
    "nr": 65,
    "name": "Jude",
    "url": "https://api.getbible.net/v2/alb/65.json",
    "sha": "0817b464b37c727c84d0a32093fcb83470111672"
  },
  "66": {
    "translation": "Albanian Bible",
    "abbreviation": "alb",
    "lang": "sq",
    "language": "Albanian",
    "direction": "LTR",
    "encoding": "UTF-8",
    "nr": 66,
    "name": "Revelation of John",
    "url": "https://api.getbible.net/v2/alb/66.json",
    "sha": "3f5be9c11caf52b2f9aec27c853f670d0782c163"
  }
}
